nonebot_plugin_quark/__init__.py
nonebot_plugin_quark/data_source.py
nonebot_plugin_quark-0.1.1.dist-info/licenses/LICENSE
nonebot_plugin_quark-0.1.1.dist-info/METADATA
nonebot_plugin_quark-0.1.1.dist-info/WHEEL
nonebot_plugin_quark-0.1.1.dist-info/top_level.txt
nonebot_plugin_quark-0.1.1.dist-info/RECORD
