Metadata-Version: 2.4
Name: nonebot-plugin-quark
Version: 0.1.1
Summary: NoneBot2 夸克云盘资源搜索插件
Author-email: fllesser <fllessive@gmail.com>
Project-URL: Repository, https://github.com/fllesser/nonebot-plugin-quark
Keywords: nonebot,nonebot2,quark,search
Requires-Python: >=3.10
License-File: LICENSE
Requires-Dist: httpx<1.0.0,>=0.26.0
Requires-Dist: tenacity>=9.0.0
Requires-Dist: nonebot2>=2.4.0
Requires-Dist: nonebot-adapter-onebot>=2.4.6
Dynamic: license-file
